connectide/__init__.py
connectide-0.0.1.dist-info/LICENSE
connectide-0.0.1.dist-info/METADATA
connectide-0.0.1.dist-info/WHEEL
connectide-0.0.1.dist-info/top_level.txt
connectide-0.0.1.dist-info/RECORD
