Metadata-Version: 2.1
Name: connectide
Version: 0.0.1
Summary: Basic Connect-4 Module
Author: Dragjon
Author-email: <magiciandragjon@gmail.com>
Keywords: python,game,board,boardgame
Classifier: Development Status :: 1 - Planning
Classifier: Intended Audience :: Developers
Classifier: Programming Language :: Python :: 3
Classifier: License :: OSI Approved :: MIT License
Classifier: Operating System :: OS Independent
License-File: LICENSE
